jsonlab/__init__.py
jsonlab/jsonlab.py
jsonlab-0.1.3.dist-info/LICENSE
jsonlab-0.1.3.dist-info/METADATA
jsonlab-0.1.3.dist-info/WHEEL
jsonlab-0.1.3.dist-info/top_level.txt
jsonlab-0.1.3.dist-info/RECORD
