Metadata-Version: 2.1
Name: jsonlab
Version: 0.1.3
Summary: json marshal and unmarshal for custom class
Home-page: https://github.com/kainhuck/jsonlab
Author: kainhuck
Author-email: kainhuck@163.com
License: UNKNOWN
Platform: UNKNOWN
Classifier: Programming Language :: Python :: 3
Classifier: License :: OSI Approved :: MIT License
Classifier: Operating System :: OS Independent
License-File: LICENSE
